wf_core_data/__init__.py
wf_core_data/airtable.py
wf_core_data/google_sheets.py
wf_core_data/transparent_classroom.py
wf_core_data/utils.py
wf_core_data/rosters/__init__.py
wf_core_data/rosters/master_roster.py
wf_core_data/rosters/shared_constants.py
wf_core_data/rosters/shared_functions.py
wf_core_data_python-1.6.0.dist-info/LICENSE
wf_core_data_python-1.6.0.dist-info/METADATA
wf_core_data_python-1.6.0.dist-info/WHEEL
wf_core_data_python-1.6.0.dist-info/top_level.txt
wf_core_data_python-1.6.0.dist-info/RECORD
